{
    "activities": [
        { "name": "Abdominal (Ab) Crunch", "image": "abdominal.jpg", "fitbitId": "2050", "fitlinxxId": "", 
                    "settings": [ ] },        
        { "name": "Back Extension", "image": "back-extension.jpg", "fitbitId": "2050", "fitlinxxId": "", 
                    "settings": [] },          
        { "name": "Bicep Curl", "image": "arm-curl.jpg", "fitbitId": "2050", "fitlinxxId": "10806", 
                    "settings": [ { "name": "Seat", "value": 7 } ] },
        { "name": "Calf Press", "image": "calf-press.jpg", "fitbitId": "2050", "fitlinxxId": "", 
                    "settings": [ { "name": "Seat", "value": 6 } ] },
        { "name": "Chest Press", "image": "chest-press.jpg", "fitbitId": "2050", "fitlinxxId": "10787", 
                    "settings": [ { "name": "Back", "value": 3 }, { "name": "Seat", "value": 2 } ] }, 
        { "name": "Hip Abduction", "image": "hip-ab-adj.jpg", "fitbitId": "2050", "fitlinxxId": "", 
                    "settings": [ { "name": "Seat", "value": 3 }, { "name": "Legs", "value": 5 } ]  },
        { "name": "Hip Adduction", "image": "hip-ab-adj.jpg", "fitbitId": "2050", "fitlinxxId": "", 
                    "settings": [ { "name": "Seat", "value": 3 }, { "name": "Legs", "value": 5 } ] }, 
        { "name": "Lateral Raise", "image": "lateral-raise.png", "fitbitId": "2050", "fitlinxxId": "", 
                    "settings": [ { "name": "Seat", "value": 5 } ] },  
        { "name": "Leg Curl", "image": "leg-curl.jpg", "fitbitId": "2050", "fitlinxxId": "10815", 
                    "settings": [] },
        { "name": "Leg Extension", "image": "leg-extension.jpg", "fitbitId": "2050", "fitlinxxId": "10811", 
                    "settings": [] },
        { "name": "Leg Press", "image": "leg-press.jpg", "fitbitId": "2050", "fitlinxxId": "10814", 
                    "settings": [ { "name": "Seat", "value": 3 }, { "name": "Legs", "value": 4 } ] },
        { "name": "Seated Row", "image": "seated-row.jpg", "fitbitId": "2050", "fitlinxxId": "10794", 
                    "settings": [ { "name": "Chest", "value": 3 }, { "name": "Seat", "value": 3 } ] },      
        { "name": "Shoulder (Overhead) Press", "image": "overhead-press.jpg", "fitbitId": "2050", "fitlinxxId": "10801", 
                    "settings": [ { "name": "Seat", "value": 2 } ]  },     
        { "name": "Tricep Dip", "image": "tricep-press.png", "fitbitId": "2050", "fitlinxxId": "10803", 
                    "settings": [ { "name": "Seat", "value": 3 } ] },  
        { "name": "Wide Grip / Lat Pulldown", "image": "lat-pulldown.png", "fitbitId": "2050", "fitlinxxId": "10791", 
                    "settings": [ { "name": "Knee", "value": 3 } ] }
    ]
}